.gitattributes
.gitignore
AUTHORS.txt
CHANGELOG
CONTRIBUTING.rst
INSTALL
LICENSE
LICENSE.euclid
LICENSE.grossini
LICENSE.python_interpreter
MANIFEST.in
README.rst
pyproject.toml
setup.py
benchmarks/collision/a0_benchmark_time_per_frame.py
benchmarks/collision/a0_bouncing_balls_Model.py
benchmarks/collision/ball32.png
benchmarks/collision/compare_collisions.py
cocos/__init__.py
cocos/batch.py
cocos/camera.py
cocos/cocosnode.py
cocos/collision_model.py
cocos/compat.py
cocos/custom_clocks.py
cocos/director.py
cocos/draw.py
cocos/euclid.py
cocos/fps.py
cocos/framegrabber.py
cocos/gl_framebuffer_object.py
cocos/grid.py
cocos/mapcolliders.py
cocos/menu.py
cocos/particle.py
cocos/particle_systems.py
cocos/path.py
cocos/rect.py
cocos/scene.py
cocos/shader.py
cocos/skeleton.py
cocos/sprite.py
cocos/text.py
cocos/tiles.py
cocos/utils.py
cocos/wired.py
cocos/actions/__init__.py
cocos/actions/base_actions.py
cocos/actions/basegrid_actions.py
cocos/actions/camera_actions.py
cocos/actions/grid3d_actions.py
cocos/actions/instant_actions.py
cocos/actions/interval_actions.py
cocos/actions/move_actions.py
cocos/actions/quadmoveby_actions.py
cocos/actions/tiledgrid_actions.py
cocos/audio/__init__.py
cocos/audio/actions.py
cocos/audio/effect.py
cocos/audio/exceptions.py
cocos/audio/music.py
cocos/layer/__init__.py
cocos/layer/base_layers.py
cocos/layer/python_interpreter.py
cocos/layer/scrolling.py
cocos/layer/util_layers.py
cocos/scenes/__init__.py
cocos/scenes/pause.py
cocos/scenes/sequences.py
cocos/scenes/transitions.py
cocos2d.egg-info/PKG-INFO
cocos2d.egg-info/SOURCES.txt
cocos2d.egg-info/dependency_links.txt
cocos2d.egg-info/not-zip-safe
cocos2d.egg-info/requires.txt
cocos2d.egg-info/top_level.txt
cocos/actions/__init__.py
cocos/actions/base_actions.py
cocos/actions/basegrid_actions.py
cocos/actions/camera_actions.py
cocos/actions/grid3d_actions.py
cocos/actions/instant_actions.py
cocos/actions/interval_actions.py
cocos/actions/move_actions.py
cocos/actions/quadmoveby_actions.py
cocos/actions/tiledgrid_actions.py
cocos/audio/AUTHORS
cocos/audio/LICENSE.pygame-ctypes
cocos/audio/__init__.py
cocos/audio/actions.py
cocos/audio/effect.py
